bettergpt/__init__.py
bettergpt-0.0.1.dist-info/LICENSE
bettergpt-0.0.1.dist-info/METADATA
bettergpt-0.0.1.dist-info/WHEEL
bettergpt-0.0.1.dist-info/top_level.txt
bettergpt-0.0.1.dist-info/RECORD
